courpr/__init__.py
courpr/learning.py
courpr-0.0.1.dist-info/METADATA
courpr-0.0.1.dist-info/WHEEL
courpr-0.0.1.dist-info/RECORD
