Metadata-Version: 2.3
Name: courpr
Version: 0.0.1
Summary: This biblioteque learn the peoples.
License: MIT
Keywords: meow
Author: JUMP10
Author-email: loskattilavr5556@gmail.com
Requires-Python: >=3.9
Classifier: License :: OSI Approved :: MIT License
Classifier: Programming Language :: Python :: 3
Classifier: Programming Language :: Python :: 3.12
Classifier: Programming Language :: Python :: 3.13
Requires-Dist: asttokens (>=2.4.1,<3.0.0)
Requires-Dist: colorama (>=0.4.6,<0.5.0)
Requires-Dist: executing (>=2.1.0,<3.0.0)
Requires-Dist: loguru (>=0.7.2,<0.8.0)
Requires-Dist: pygments (>=2.18.0,<3.0.0)
Requires-Dist: pytest (>=8.3.3,<9.0.0)
Requires-Dist: rich (>=13.8.1,<14.0.0)
Requires-Dist: ruff (>=0.6.8,<0.7.0)
